ImgTkinter/ImgTkinter.py
ImgTkinter/__init__.py
imgtkinter-1.0.3.dist-info/licenses/LICENSE
imgtkinter-1.0.3.dist-info/METADATA
imgtkinter-1.0.3.dist-info/WHEEL
imgtkinter-1.0.3.dist-info/entry_points.txt
imgtkinter-1.0.3.dist-info/top_level.txt
imgtkinter-1.0.3.dist-info/RECORD
