Metadata-Version: 2.4
Name: ImgTkinter
Version: 1.0.3
Summary: A powerful image classification and management tool
Home-page: https://github.com/peng0928/ImgTkinter
Author: Penr
Author-email: 1944542244@qq.com
Project-URL: Bug Reports, https://github.com/peng0928/ImgTkinter/issues
Project-URL: Source, https://github.com/peng0928/ImgTkinter
Keywords: image,classification,management,PyQt5,desktop
Classifier: Development Status :: 4 - Beta
Classifier: Intended Audience :: End Users/Desktop
Classifier: Topic :: Multimedia :: Graphics
Classifier: License :: OSI Approved :: MIT License
Classifier: Programming Language :: Python :: 3
Classifier: Programming Language :: Python :: 3.6
Classifier: Programming Language :: Python :: 3.7
Classifier: Programming Language :: Python :: 3.8
Classifier: Programming Language :: Python :: 3.9
Classifier: Operating System :: OS Independent
Requires-Python: >=3.6
License-File: LICENSE
Requires-Dist: PyQt5>=5.15.0
Requires-Dist: pypinyin>=0.44.0
Dynamic: author
Dynamic: author-email
Dynamic: classifier
Dynamic: description
Dynamic: description-content-type
Dynamic: home-page
Dynamic: keywords
Dynamic: license-file
Dynamic: project-url
Dynamic: requires-dist
Dynamic: requires-python
Dynamic: summary
